{
  "token": {
    "_id": "-NLyZy6iK37_e4exgT4H",
    "_pageid": "-LmGrWkmx6c7P_K5JrS5",
    "left": 910,
    "top": 420,
    "width": 70,
    "height": 70,
    "rotation": 0,
    "layer": "objects",
    "isdrawing": false,
    "flipv": false,
    "fliph": false,
    "imgsrc": "https://s3.amazonaws.com/files.d20.io/images/28450281/heCscf51qjn8zRRwUPHYjA/thumb.png?5319634",
    "name": "Dwarf Doodid",
    "gmnotes": "",
    "controlledby": "",
    "bar1_value": 10,
    "bar1_max": 34,
    "bar1_link": "-NLy4nxan1PCQuQy_5LA",
    "bar2_value": "11",
    "bar2_max": "",
    "bar2_link": "-NLy4nxWn1-03j3NmABR",
    "bar3_value": "",
    "bar3_max": "",
    "bar3_link": "-NLyY4pL2NkAKe5XaNuM",
    "represents": "-NLy4nr_SuCrWwvdu840",
    "aura1_radius": "",
    "aura1_color": "#FFFF99",
    "aura1_square": false,
    "aura2_radius": "",
    "aura2_color": "#59E594",
    "aura2_square": false,
    "tint_color": "transparent",
    "statusmarkers": "",
    "showname": false,
    "showplayers_name": false,
    "showplayers_bar1": false,
    "showplayers_bar2": false,
    "showplayers_bar3": false,
    "showplayers_aura1": false,
    "showplayers_aura2": false,
    "playersedit_name": true,
    "playersedit_bar1": true,
    "playersedit_bar2": true,
    "playersedit_bar3": true,
    "playersedit_aura1": true,
    "playersedit_aura2": true,
    "light_radius": 5,
    "light_dimradius": -5,
    "light_otherplayers": false,
    "light_hassight": true,
    "light_angle": 360,
    "light_losangle": 360,
    "light_multiplier": 1,
    "adv_fow_view_distance": "",
    "sides": "",
    "currentSide": 0,
    "lastmove": "873,394",
    "_type": "graphic",
    "_subtype": "token",
    "_cardid": "",
    "has_bright_light_vision": true,
    "has_night_vision": true,
    "night_vision_tint": null,
    "night_vision_distance": 0,
    "emits_bright_light": true,
    "bright_light_distance": 20,
    "emits_low_light": false,
    "low_light_distance": 20,
    "has_limit_field_of_vision": false,
    "limit_field_of_vision_center": 0,
    "limit_field_of_vision_total": 0,
    "has_limit_field_of_night_vision": false,
    "limit_field_of_night_vision_center": 0,
    "limit_field_of_night_vision_total": 0,
    "has_directional_bright_light": false,
    "directional_bright_light_total": 0,
    "directional_bright_light_center": 0,
    "has_directional_dim_light": false,
    "directional_dim_light_total": 0,
    "directional_dim_light_center": 0,
    "light_sensitivity_multiplier": 100,
    "tooltip": "",
    "show_tooltip": false,
    "night_vision_effect": null,
    "dim_light_opacity": "0.75",
    "bar_location": null,
    "compact_bar": null,
    "lightColor": "transparent",
    "lockMovement": false
  },
  "shifterId": "Dwarf Doodid",
  "shifter": {
    "settings": {
      "ID": "-NLoPnEXNN1Zj2D1jS6H",
      "character": "Dwarf Doodid",
      "size": "normal",
      "isdruid": true,
      "isnpc": false,
      "currshape": "Brown Bear",
      "SENSES": {
        "light_radius": 5,
        "light_dimradius": -5,
        "light_otherplayers": false,
        "light_hassight": true,
        "light_angle": 360,
        "light_losangle": 360,
        "light_multiplier": 1,
        "OVERRIDE_SENSES": false
      }
    },
    "shapes": {
      "Brown Bear": {
        "ID": "-NLy4nr_SuCrWwvdu840",
        "character": "Dwarf Doodid - Brown Bear",
        "size": "auto",
        "isDuplicate": true,
        "stats_cache": {
          "stats": { "strength": 19, "dexterity": 10, "constitution": 16, "intelligence": 2, "wisdom": 13, "charisma": 7 },
          "modifiers": { "strength": 4, "dexterity": 0, "constitution": 3, "intelligence": -4, "wisdom": 1, "charisma": -2 },
          "saves": { "strength": 4, "dexterity": 0, "constitution": 3, "intelligence": -4, "wisdom": 1, "charisma": -2 },
          "skills": {
            "athletics": 4,
            "acrobatics": 0,
            "sleight_of_hand": 0,
            "stealth": 0,
            "arcana": -4,
            "history": -4,
            "investigation": -4,
            "nature": -4,
            "religion": -4,
            "animal_handling": 1,
            "insight": 1,
            "medicine": 1,
            "perception": 3,
            "survival": 1,
            "deception": -2,
            "intimidation": -2,
            "performance": -2,
            "persuasion": -2
          }
        },
        "SENSES": {
          "light_radius": 5,
          "light_dimradius": -5,
          "light_otherplayers": false,
          "light_hassight": true,
          "light_angle": 360,
          "light_losangle": 360,
          "light_multiplier": 1,
          "OVERRIDE_SENSES": false
        }
      }
    }
  },
  "shifterCharacterId": "-NLoPnEXNN1Zj2D1jS6H",
  "shifterCharacter": {
    "name": "Dwarf Doodid",
    "bio": "",
    "gmnotes": "",
    "_defaulttoken": 1673936086225,
    "archived": false,
    "inplayerjournals": "-NFqz5OnWb1nZrH8EpDD",
    "controlledby": "-NFqz5OnWb1nZrH8EpDD",
    "_id": "-NLoPnEXNN1Zj2D1jS6H",
    "_type": "character",
    "avatar": "https://s3.amazonaws.com/files.d20.io/images/322929460/RNcMDzgdtaQbBRg_MJR5Dw/med.png?1673769434"
  },
  "shifterControlledby": "-NFqz5OnWb1nZrH8EpDD"
}
